avicortex/__init__.py
avicortex/builders.py
avicortex/datasets.py
avicortex/data/adni3_region_mapping.csv
avicortex/data/openneuro_all_dktatlas.csv
avicortex/data/openneuro_baseline_destrieux.csv
avicortex/data/openneuro_baseline_dktatlas.csv
avicortex/data/openneuro_followup_destrieux.csv
avicortex/data/openneuro_followup_dktatlas.csv
avicortex/data/openneuro_participants.csv
avicortex/data/openneuro_participants_all_timepoints.csv
avicortex/data/region_names_destrieux.csv
avicortex/data/region_names_dktatlas.csv
avicortex/freesurfer/__init__.py
avicortex/freesurfer/cli.py
avicortex/freesurfer/exceptions.py
avicortex/freesurfer/parsers.py
avicortex/freesurfer/reader.py
avicortex/freesurfer/types.py
avicortex/freesurfer/utils.py
avicortex/freesurfer/writer.py
avicortex/fs_utils/stats2table_bash.sh
avicortex-1.0.0.dist-info/LICENSE
avicortex-1.0.0.dist-info/METADATA
avicortex-1.0.0.dist-info/WHEEL
avicortex-1.0.0.dist-info/entry_points.txt
avicortex-1.0.0.dist-info/top_level.txt
avicortex-1.0.0.dist-info/RECORD
