Metadata-Version: 2.1
Name: avicortex
Version: 1.0.0
Summary: Python functions and classes to build connectivity graphs and datasets from Freesurfer's brain cortical measurements.
Author-email: Oytun Demirbilek <oytun1996@gmail.com>
License: Apache License
Project-URL: Code Repository, https://github.com/oytundemirbilek/avicortex
Project-URL: Documentation, https://pages.github.com
Keywords: graphs,brain,freesurfer,connectome
Classifier: Operating System :: OS Independent
Classifier: Programming Language :: Python
Classifier: Programming Language :: Python :: 3
Classifier: Programming Language :: Python :: 3.7
Classifier: Programming Language :: Python :: 3.8
Classifier: Programming Language :: Python :: 3.9
Classifier: Programming Language :: Python :: 3.10
Classifier: Programming Language :: Python :: 3.11
Classifier: Topic :: Scientific/Engineering
Classifier: Topic :: Scientific/Engineering :: Artificial Intelligence
Classifier: Topic :: Scientific/Engineering :: Medical Science Apps.
Classifier: Topic :: Scientific/Engineering :: Information Analysis
Classifier: Topic :: Software Development
Classifier: Topic :: Software Development :: Libraries
Classifier: Typing :: Typed
Requires-Python: >=3.7
License-File: LICENSE
Requires-Dist: numpy
Requires-Dist: pandas
Requires-Dist: scikit-learn
Requires-Dist: torch
Requires-Dist: torch-geometric
Provides-Extra: docs
Requires-Dist: sphinx ; extra == 'docs'
Requires-Dist: sphinx-toolbox ; extra == 'docs'
Requires-Dist: sphinx-rtd-theme ; extra == 'docs'
Requires-Dist: furo ; extra == 'docs'
Provides-Extra: lint
Requires-Dist: isort ; extra == 'lint'
Requires-Dist: black ; extra == 'lint'
Requires-Dist: pyupgrade ; extra == 'lint'
Requires-Dist: flake8 ; extra == 'lint'
Requires-Dist: pep8-naming ; extra == 'lint'
Requires-Dist: flake8-pyproject ; extra == 'lint'
Requires-Dist: flake8-noqa ; extra == 'lint'
Requires-Dist: flake8-bugbear ; extra == 'lint'
Requires-Dist: flake8-builtins ; extra == 'lint'
Requires-Dist: flake8-docstrings ; extra == 'lint'
Requires-Dist: flake8-comprehensions ; extra == 'lint'
Requires-Dist: flake8-simplify ; extra == 'lint'
Requires-Dist: flake8-logging ; extra == 'lint'
Requires-Dist: pyright ; extra == 'lint'
Requires-Dist: bandit ; extra == 'lint'
Requires-Dist: ruff ; extra == 'lint'
Requires-Dist: mypy ; extra == 'lint'
Requires-Dist: types-setuptools ; extra == 'lint'
Requires-Dist: pydantic ; extra == 'lint'
Requires-Dist: yamllint ; extra == 'lint'
Requires-Dist: codespell[toml] ; extra == 'lint'
Requires-Dist: gitlint ; extra == 'lint'
Requires-Dist: pre-commit ; extra == 'lint'
Provides-Extra: test
Requires-Dist: pytest ; extra == 'test'
Requires-Dist: pytest-cov ; extra == 'test'
Requires-Dist: pytest-xdist ; extra == 'test'
Requires-Dist: hypothesis[pytest] ; extra == 'test'
Requires-Dist: tox ; extra == 'test'
